charlabs/logging/__init__.py
charlabs/logging/py.typed
charlabs/logging/_base/logs_settings.py
charlabs/logging/_base/setup_logs.py
charlabs/logging/_base/task_logger.py
charlabs/logging/default/__init__.py
charlabs/logging/default/logs_settings.py
charlabs/logging/default/setup_logs.py
charlabs/logging/default/task_logger.py
charlabs/logging/structlog/__init__.py
charlabs/logging/structlog/logs_settings.py
charlabs/logging/structlog/processors.py
charlabs/logging/structlog/setup_logs.py
charlabs/logging/structlog/task_logger.py
charlabs_logging-1.0.0.dist-info/METADATA
charlabs_logging-1.0.0.dist-info/WHEEL
charlabs_logging-1.0.0.dist-info/top_level.txt
charlabs_logging-1.0.0.dist-info/RECORD
