Metadata-Version: 2.4
Name: charlabs-logging
Version: 1.0.0
Summary: Add your description here
Requires-Python: >=3.12
Requires-Dist: pydantic-settings>=2.10.1
Requires-Dist: pyyaml>=6.0.2
